helloworld.py
hellosamjones-0.0.1.dist-info/DESCRIPTION.rst
hellosamjones-0.0.1.dist-info/METADATA
hellosamjones-0.0.1.dist-info/RECORD
hellosamjones-0.0.1.dist-info/WHEEL
hellosamjones-0.0.1.dist-info/metadata.json
hellosamjones-0.0.1.dist-info/top_level.txt
