Metadata-Version: 2.0
Name: hellosamjones
Version: 0.0.1
Summary: Say Hello name
Home-page: https://github.com/samjones310/helloworld
Author: Sam Jones
Author-email: UNKNOWN
License: UNKNOWN
Platform: UNKNOWN
Classifier: Programming Language :: Python :: 3
Classifier: Programming Language :: Python :: 3.6
Classifier: Programming Language :: Python :: 3.7
Classifier: License :: OSI Approved :: GNU General Public License v2 or later (GPLv2+)
Classifier: Operating System :: OS Independent
